Bep/__init__.py
Bep/actions.py
Bep/package.py
Bep/run.py
Bep/cmds/__init__.py
Bep/cmds/install.py
Bep/cmds/list_packages.py
Bep/cmds/remove_packages.py
Bep/cmds/turn_off.py
Bep/cmds/turn_on.py
Bep/cmds/update_packages.py
Bep/core/__init__.py
Bep/core/release_info.py
Bep/core/usage.py
Bep/core/utils.py
Bep/core/utils_db.py
Bep/languages/__init__.py
Bep/languages/languages.py
Bep/scripts/__init__.py
Bep/scripts/bep_script.py
Bep/tests/__init__.py
Bep/tests/test_commands.py
bep-0.7.1.dist-info/DESCRIPTION.rst
bep-0.7.1.dist-info/METADATA
bep-0.7.1.dist-info/RECORD
bep-0.7.1.dist-info/WHEEL
bep-0.7.1.dist-info/entry_points.txt
bep-0.7.1.dist-info/metadata.json
bep-0.7.1.dist-info/top_level.txt
