Metadata-Version: 2.0
Name: bep
Version: 0.7.1
Summary: A tool to make package management from source easier.
Home-page: http://www.github.com/b-e-p/bep.git
Author: jason gors
Author-email: jasonDOTgorsATgmailDOTcom
License: Type license() to see the full license text
Platform: UNKNOWN
Classifier: Programming Language :: Python :: 2.7
Classifier: Programming Language :: Python :: 3
